{
    "id_user": 6,
    "name_user": "rievaldy",
    "email_user": "rievaldy3235@gmail.com",
    "phone_number": null,
    "address_user": "jl.j.jali rt 05/02",
    "id_company": 1122,
    "chat_history": [
        {
            "context": "login account",
            "action": [
                {
                    "desc": "id_user",
                    "value": 6
                },
                {
                    "desc": "name_user",
                    "value": "rievaldy"
                },
                {
                    "desc": "email_user",
                    "value": "rievaldy3235@gmail.com"
                },
                {
                    "desc": "phone_number",
                    "value": "0895330343387"
                },
                {
                    "desc": "address_user",
                    "value": "jl.j.jali rt 05/02"
                },
                {
                    "desc": "id_company",
                    "value": 1122
                }
            ]
        },
        {
            "context": "greetings",
            "action": []
        },
        {
            "context": "greetings",
            "action": []
        }
    ]
}